Workbook
Name CD.I24: Comparador!$K$29
Name CD.I25: Comparador!$L$29
Name CD.I26: Comparador!$M$29
Name Data2024: Comparador!$K$28
Name Data2025: Comparador!$L$28
Name Data2026: Comparador!$M$28
Name IPCA24: Comparador!$K$30
Name IPCA25: Comparador!$L$30
Name IPCA26: Comparador!$M$30
Name Juros24: Comparador!$K$29
Name Vencimento: Comparador!$F$13
Name Vencimento1: Comparador!$F$13
Name Vencimento2: Comparador!$F$15
Name Vencimento3: Comparador!$F$17
Name Vencimento4: Comparador!$F$19
Name Vencimento5: Comparador!$F$21
Name Vencimento6: Comparador!$F$23

Sheet Capa
K3: Como utilizar a planilha:
I5: Passo 1 | K5: Abra o site da sua corretora e acesse a área de Renda Fixa para visualizar os produtos disponíveis.
I6: Passo 2 | K6: Selecionar na coluna ativo qual será o título que pretendemos investir. (Ex: CDB. LCI, LCA, CRI, CRA)
I7: Passo 3 | K7: Selecionar o modelo de rentabilidade. (Ex: Pré-fixada, pós-fixada ou IPCA+)
I8: Passo 4 | K8: Inserir a taxa do título, da mesma forma que aparece na página da corretora. (Ex: 120%, 10%, 6%)
I9: Passo 5 | K9: Inserir a data de vencimento do título (Ex: 04/10/2027)
K20: Observação:
K21: Reforçamos que o objetivo da ferramenta é facilitar o cálculo da rentabilidade líquida e que são calculadas de acordo com estimativas da taxa básica de juros e inflação futuras.

Sheet Comparador
K11: Regra de Imposto de Renda Atual | N11: Nova Regra de Imposto de Renda
C12: Ativo | D12: Indexador | E12: % do CDI ou Taxa préfixada | F12: Vencimento | G12: Dias | H12: Taxa bruta | I12: Taxa nominal | J12: IR atual | K12: Taxa nominal líquida | L12: Taxa nominal líquida em %CDI | M12: Novo IR* | N12: Taxa nominal líquida | O12: Taxa nominal líquida em %CDI
B13: =_xlfn.CONCAT(C13," ",D13) -> CRI IPCA+ | C13: CRI | D13: IPCA+ | E13: 0.099 | F13: 49841 | G13: =F13-TODAY() -> 3868 | H13: =IF(D13="IPCA+",E13+Dados!G28,E13) -> 0.13953992 | I13: =IF(D13=Dados!$C$14,Comparador!H13*Dados!G14,Comparador!H13) -> 0.13953992 | J13: =IF(C13="Poupança",0,IF(OR(C13=Dados!$B$14,C13=Dados!$B$19,C13=Dados!$B$20,C13=Dados!$B$21,C13=Dados!$B$22),IF(F13-TODAY()>=721,D$32,IF(F13-TODAY()>=361,D$31,IF(F13-TODAY()>=181,D$30,D$29))),0)) -> 0 | K13: =I13*(1-J13) -> 0.13953992 | L13: =K13/Dados!$G14 -> 1.2850499 | M13: =IF(C13="Poupança",0,IF(OR(C13=Dados!$B$14,C13=Dados!$B$19,C13=Dados!$B$20,C13=Dados!$B$21,C13=Dados!$B$22),$D$35,$D$36)) -> 0.05 | N13: =I13*(1-M13) -> 0.13256293 | O13: =N13/Dados!$G14 -> 1.2207974
B15: =_xlfn.CONCAT(C15," ",D15) -> CRA IPCA+ | C15: CRA | D15: IPCA+ | E15: 0.0732 | F15: 56751 | G15: =F15-TODAY() -> 10778 | H15: =IF(D15="IPCA+",E15+Dados!G30,E15) -> 0.11339374 | I15: =IF(D15=Dados!$C$14,Comparador!H15*Dados!G16,Comparador!H15) -> 0.11339374 | J15: =IF(C15="Poupança",0,IF(OR(C15=Dados!$B$14,C15=Dados!$B$19,C15=Dados!$B$20,C15=Dados!$B$21,C15=Dados!$B$22),IF(F15-TODAY()>=721,D$32,IF(F15-TODAY()>=361,D$31,IF(F15-TODAY()>=181,D$30,D$29))),0)) -> 0 | K15: =I15*(1-J15) -> 0.11339374 | L15: =K15/Dados!$G16 -> 1.0668735 | M15: =IF(C15="Poupança",0,IF(OR(C15=Dados!$B$14,C15=Dados!$B$19,C15=Dados!$B$20,C15=Dados!$B$21,C15=Dados!$B$22),$D$35,$D$36)) -> 0.05 | N15: =I15*(1-M15) -> 0.10772405 | O15: =N15/Dados!$G16 -> 1.0135298
B17: =_xlfn.CONCAT(C17," ",D17) -> Debenture Incentivada IPCA+ | C17: Debenture Incentivada | D17: IPCA+ | E17: 0.0695 | F17: 47253 | G17: =F17-TODAY() -> 1280 | H17: =IF(D17="IPCA+",E17+Dados!G32,E17) -> 0.11113244 | I17: =IF(D17=Dados!$C$14,Comparador!H17*Dados!G18,Comparador!H17) -> 0.11113244 | J17: =IF(C17="Poupança",0,IF(OR(C17=Dados!$B$14,C17=Dados!$B$19,C17=Dados!$B$20,C17=Dados!$B$21,C17=Dados!$B$22),IF(F17-TODAY()>=721,D$32,IF(F17-TODAY()>=361,D$31,IF(F17-TODAY()>=181,D$30,D$29))),0)) -> 0 | K17: =I17*(1-J17) -> 0.11113244 | L17: =K17/Dados!$G18 -> 0.95906696 | M17: =IF(C17="Poupança",0,IF(OR(C17=Dados!$B$14,C17=Dados!$B$19,C17=Dados!$B$20,C17=Dados!$B$21,C17=Dados!$B$22),$D$35,$D$36)) -> 0.05 | N17: =I17*(1-M17) -> 0.10557582 | O17: =N17/Dados!$G18 -> 0.91111362
B19: =_xlfn.CONCAT(C19," ",D19) -> LTN Pré-fixado | C19: LTN | D19: Pré-fixado | E19: 0.1359 | F19: 47849 | G19: =F19-TODAY() -> 1876 | H19: =IF(D19="IPCA+",E19+Dados!G34,E19) -> 0.1359 | I19: =IF(D19=Dados!$C$14,Comparador!H19*Dados!G20,Comparador!H19) -> 0.1359 | J19: =IF(C19="Poupança",0,IF(OR(C19=Dados!$B$14,C19=Dados!$B$19,C19=Dados!$B$20,C19=Dados!$B$21,C19=Dados!$B$22),IF(F19-TODAY()>=721,D$32,IF(F19-TODAY()>=361,D$31,IF(F19-TODAY()>=181,D$30,D$29))),0)) -> 0.15 | K19: =I19*(1-J19) -> 0.115515 | L19: =K19/Dados!$G20 -> 1.0276323 | M19: =IF(C19="Poupança",0,IF(OR(C19=Dados!$B$14,C19=Dados!$B$19,C19=Dados!$B$20,C19=Dados!$B$21,C19=Dados!$B$22),$D$35,$D$36)) -> 0.175 | N19: =I19*(1-M19) -> 0.1121175 | O19: =N19/Dados!$G20 -> 0.9974078
B21: =_xlfn.CONCAT(C21," ",D21) -> LFT Pós-fixado | C21: LFT | D21: Pós-fixado | E21: 1 | F21: 49324 | G21: =F21-TODAY() -> 3351 | H21: =IF(D21="IPCA+",E21+Dados!G36,E21) -> 1 | I21: =IF(D21=Dados!$C$14,Comparador!H21*Dados!G22,Comparador!H21) -> 0.10914164 | J21: =IF(C21="Poupança",0,IF(OR(C21=Dados!$B$14,C21=Dados!$B$19,C21=Dados!$B$20,C21=Dados!$B$21,C21=Dados!$B$22),IF(F21-TODAY()>=721,D$32,IF(F21-TODAY()>=361,D$31,IF(F21-TODAY()>=181,D$30,D$29))),0)) -> 0.15 | K21: =I21*(1-J21) -> 0.092770392 | L21: =K21/Dados!$G22 -> 0.85 | M21: =IF(C21="Poupança",0,IF(OR(C21=Dados!$B$14,C21=Dados!$B$19,C21=Dados!$B$20,C21=Dados!$B$21,C21=Dados!$B$22),$D$35,$D$36)) -> 0.175 | N21: =I21*(1-M21) -> 0.090041851 | O21: =N21/Dados!$G22 -> 0.825
B23: =_xlfn.CONCAT(C23," ",D23) -> Poupança | C23: Poupança | E23: =(1.005+0.0007)^12-1 -> 0.07058561 | G23: =F23-TODAY() -> -45973 | H23: =IF(D23="IPCA+",E23+Dados!G38,E23) -> 0.07058561 | I23: =IF(D23=Dados!$C$14,Comparador!H23*Dados!G24,Comparador!H23) -> 0.07058561 | J23: =IF(C23="Poupança",0,IF(OR(C23=Dados!$B$14,C23=Dados!$B$19,C23=Dados!$B$20,C23=Dados!$B$21),IF(F23-TODAY()>=721,D$32,IF(F23-TODAY()>=361,D$31,IF(F23-TODAY()>=181,D$30,D$29))),0)) -> 0 | K23: =I23*(1-J23) -> 0.07058561 | L23: =K23/Dados!$G24 -> 0.47057073 | M23: =IF(C23="Poupança",0,IF(OR(C23=Dados!$B$14,C23=Dados!$B$19,C23=Dados!$B$20,C23=Dados!$B$21,C23=Dados!$B$22),$D$35,0)) -> 0 | N23: =I23*(1-M23) -> 0.07058561 | O23: =N23/Dados!$G24 -> 0.47057073
B25: * Assumimos a TR de 0,07% ao mês para Poupança
B27: Atual Tabela regressiva de IR - Renda Fixa | J27: Premissas macroeconômicas
B28: Período | D28: Alíquota | K28: 2025 | L28: 2026 | M28: 2027
B29: Até 180 dias | D29: 0.225 | J29: CDI | K29: 0.15 | L29: 0.1375 | M29: 0.105
B30: Entre 180 e 360 dias | D30: 0.2 | J30: IPCA | K30: 0.0507 | L30: 0.0443 | M30: 0.04
B31: Entre 360 e 720 dias | D31: 0.175
B32: Acima de 720 dias | D32: 0.15 | J32: Premissas Relatório FOCUS
K33: 2025 | L33: 2026 | M33: 2027
B34: Proposta de Nova Regra de IR - Renda Fixa | J34: SELIC (Final) | K34: 0.15 | L34: =(15%+12.5%)/2 -> 0.1375
B35: Alíquota não isentos | D35: 0.175 | J35: IPCA (Acumulado) | K35: 0.0507 | L35: 0.0443 | M35: 0.04
B36: Alíquota isentos | D36: 0.05
B37: * Os valores de 5% e 17,5% ainda estão sendo discutidos no governo.
B38: Essa é apenas uma simulação de como podem ficar os impostos
B40: Como ler o resultado:
B41: 1) O gráfico 1 mostra o comparativo entre as taxas de rentabilidade absolutas, já deduzidas de imposto de renda, ou seja, quanto um título deve render em termos perncentuais ao ano.
B42: Além disso, nesse gráfico, também podemos ver uma comparação entre a rentabildiade no modelo atual de imposto de renda (laranja) e o quanto seria com o novo modelo de imposto
B43: de renda proposto pelo governo (preto)
B44: 2) O gráfico 2 mostra o comparativo entre as taxas como % do CDI, já deduzidas de imposto de renda, ou seja, o quanto os títulos devem render em relação ao CDI projetado para o
B45: período. Assim como no gráfico 1, também podemos comparar a diferença entre o modelo atual de imposto de renda (laranja) e o novo modelo de IR proposto pelo governo (petro)

Sheet Dados
B8: Data de Atualização: | C8: 45874
B9: Analista: | C9: João Neves | H9: Inputs Clientes
H10: Inputs Atualização
I11: Cálculos
B12: Botões | J12: Dias (Total) | K12: =YEAR(K13) -> 2025 | L12: =YEAR(L13) -> 2026 | M12: =YEAR(M13) -> 2027 | O12: =YEAR(O13) -> 2025 | P12: =YEAR(P13) -> 2026 | Q12: =YEAR(Q13) -> 2027
B13: Ativos | C13: Indexadores | D13: Prazos | G13: CDI | I13: Vencimentos | J13: =+TODAY() -> 45973 | K13: 46022 | L13: 46387 | M13: 46752 | O13: =K13 -> 46022 | P13: =L13 -> 46387 | Q13: =M13 -> 46752
B14: CDB | C14: Pós-fixado | D14: Até 180 dias | G14: =U14 -> 0.10858717 | I14: =Comparador!F13 -> 49841 | J14: =I14-$J$13 -> 3868 | K14: =IF(I14<$K$13,J14,$K$13-$J$13) -> 49 | L14: =IF(I14<$L$13,IF(I14-$K$13<0,0,I14-$K$13),IF(I14<$L$13,$L$13-I14,365)) -> 365 | M14: =IF(I14<$M$13,IF(I14-$L$13<0,0,I14-$L$13),IF(I14<$M$13,$M$13-I14,365-($M$13-I14))) -> 3454 | O14: =(1+Comparador!$K$29)^(Dados!K14/365) -> 1.0189397 | P14: =(1+Comparador!$L$29)^(Dados!L14/365) -> 1.1375 | Q14: =(1+Comparador!$M$29)^(Dados!M14/365) -> 2.572396 | S14: =O14*P14*Q14-1 -> 1.9815199 | U14: =(1+S14)^(365/J14)-1 -> 0.10858717
B15: CRI | C15: Pré-fixado | D15: Entre 180 e 360 dias
B16: CRA | C16: IPCA+ | D16: Entre 360 e 720 dias | G16: =U16 -> 0.10628602 | I16: =Comparador!F15 -> 56751 | J16: =I16-$J$13 -> 10778 | K16: =IF(I16<$K$13,J16,$K$13-$J$13) -> 49 | L16: =IF(I16<$L$13,IF(I16-$K$13<0,0,I16-$K$13),IF(I16<$L$13,$L$13-I16,365)) -> 365 | M16: =IF(I16<$M$13,IF(I16-$L$13<0,0,I16-$L$13),IF(I16<$M$13,$M$13-I16,365-($M$13-I16))) -> 10364 | O16: =(1+Comparador!$K$29)^(Dados!K16/365) -> 1.0189397 | P16: =(1+Comparador!$L$29)^(Dados!L16/365) -> 1.1375 | Q16: =(1+Comparador!$M$29)^(Dados!M16/365) -> 17.031429 | S16: =O16*P16*Q16-1 -> 18.740174 | U16: =(1+S16)^(365/J16)-1 -> 0.10628602
B17: LCI | D17: Acima de 720 dias
B18: LCA | G18: =U18 -> 0.11587558 | I18: =Comparador!F17 -> 47253 | J18: =I18-$J$13 -> 1280 | K18: =IF(I18<$K$13,J18,$K$13-$J$13) -> 49 | L18: =IF(I18<$L$13,IF(I18-$K$13<0,0,I18-$K$13),IF(I18<$L$13,$L$13-I18,365)) -> 365 | M18: =IF(I18<$M$13,IF(I18-$L$13<0,0,I18-$L$13),IF(I18<$M$13,$M$13-I18,365-($M$13-I18))) -> 866 | O18: =(1+Comparador!$K$29)^(Dados!K18/365) -> 1.0189397 | P18: =(1+Comparador!$L$29)^(Dados!L18/365) -> 1.1375 | Q18: =(1+Comparador!$M$29)^(Dados!M18/365) -> 1.2673059 | S18: =O18*P18*Q18-1 -> 0.46886317 | U18: =(1+S18)^(365/J18)-1 -> 0.11587558
B19: LTN
B20: NTN-B | G20: =U20 -> 0.11240889 | I20: =Comparador!F19 -> 47849 | J20: =I20-$J$13 -> 1876 | K20: =IF(I20<$K$13,J20,$K$13-$J$13) -> 49 | L20: =IF(I20<$L$13,IF(I20-$K$13<0,0,I20-$K$13),IF(I20<$L$13,$L$13-I20,365)) -> 365 | M20: =IF(I20<$M$13,IF(I20-$L$13<0,0,I20-$L$13),IF(I20<$M$13,$M$13-I20,365-($M$13-I20))) -> 1462 | O20: =(1+Comparador!$K$29)^(Dados!K20/365) -> 1.0189397 | P20: =(1+Comparador!$L$29)^(Dados!L20/365) -> 1.1375 | Q20: =(1+Comparador!$M$29)^(Dados!M20/365) -> 1.4917179 | S20: =O20*P20*Q20-1 -> 0.72896657 | U20: =(1+S20)^(365/J20)-1 -> 0.11240889
B21: LFT
B22: Debenture | G22: =U22 -> 0.10914164 | I22: =Comparador!F21 -> 49324 | J22: =I22-$J$13 -> 3351 | K22: =IF(I22<$K$13,J22,$K$13-$J$13) -> 49 | L22: =IF(I22<$L$13,IF(I22-$K$13<0,0,I22-$K$13),IF(I22<$L$13,$L$13-I22,365)) -> 365 | M22: =IF(I22<$M$13,IF(I22-$L$13<0,0,I22-$L$13),IF(I22<$M$13,$M$13-I22,365-($M$13-I22))) -> 2937 | O22: =(1+Comparador!$K$29)^(Dados!K22/365) -> 1.0189397 | P22: =(1+Comparador!$L$29)^(Dados!L22/365) -> 1.1375 | Q22: =(1+Comparador!$M$29)^(Dados!M22/365) -> 2.2331497 | S22: =O22*P22*Q22-1 -> 1.5883185 | U22: =(1+S22)^(365/J22)-1 -> 0.10914164
B23: Debenture Incentivada
G24: =U24 -> 0.15 | I24: =Comparador!F23 -> 0 | J24: =I24-$J$13 -> -45973 | K24: =IF(I24<$K$13,J24,$K$13-$J$13) -> -45973 | L24: =IF(I24<$L$13,IF(I24-$K$13<0,0,I24-$K$13),IF(I24<$L$13,$L$13-I24,365)) -> 0 | M24: =IF(I24<$M$13,IF(I24-$L$13<0,0,I24-$L$13),IF(I24<$M$13,$M$13-I24,365-($M$13-I24))) -> 0 | O24: =(1+Comparador!$K$29)^(Dados!K24/365) -> 2.2641184e-08 | P24: =(1+Comparador!$L$29)^(Dados!L24/365) -> 1 | Q24: =(1+Comparador!$M$29)^(Dados!M24/365) -> 1 | S24: =O24*P24*Q24-1 -> -0.99999998 | U24: =(1+S24)^(365/J24)-1 -> 0.15
G27: IPCA | J27: =J13 -> 45973 | K27: =K13 -> 46022 | L27: =L13 -> 46387 | M27: =M13 -> 46752 | O27: =K27 -> 46022 | P27: =L27 -> 46387 | Q27: =M27 -> 46752
G28: =U28 -> 0.040539924 | I28: =Comparador!F13 -> 49841 | J28: =I28-$J$13 -> 3868 | K28: =IF(I28<$K$13,J28,$K$13-$J$13) -> 49 | L28: =IF(I28<$L$13,IF(I28-$K$13<0,0,I28-$K$13),IF(I28<$L$13,$L$13-I28,365)) -> 365 | M28: =IF(I28<$M$13,IF(I28-$L$13<0,0,I28-$L$13),IF(I28<$M$13,$M$13-I28,365-($M$13-I28))) -> 3454 | O28: =(1+Comparador!$K$30)^(Dados!K28/365) -> 1.0066615 | P28: =(1+Comparador!$L$30)^(Dados!L28/365) -> 1.0443 | Q28: =(1+Comparador!$M$30)^(Dados!M28/365) -> 1.4493949 | S28: =O28*P28*Q28-1 -> 0.5236859 | U28: =(1+S28)^(365/J28)-1 -> 0.040539924
G30: =U30 -> 0.040193735 | I30: =Comparador!F15 -> 56751 | J30: =I30-$J$13 -> 10778 | K30: =IF(I30<$K$13,J30,$K$13-$J$13) -> 49 | L30: =IF(I30<$L$13,IF(I30-$K$13<0,0,I30-$K$13),IF(I30<$L$13,$L$13-I30,365)) -> 365 | M30: =IF(I30<$M$13,IF(I30-$L$13<0,0,I30-$L$13),IF(I30<$M$13,$M$13-I30,365-($M$13-I30))) -> 10364 | O30: =(1+Comparador!$K$30)^(Dados!K30/365) -> 1.0066615 | P30: =(1+Comparador!$L$30)^(Dados!L30/365) -> 1.0443 | Q30: =(1+Comparador!$M$30)^(Dados!M30/365) -> 3.0454642 | S30: =O30*P30*Q30-1 -> 2.2015643 | U30: =(1+S30)^(365/J30)-1 -> 0.040193735
G32: =U32 -> 0.04163244 | I32: =Comparador!F17 -> 47253 | J32: =I32-$J$13 -> 1280 | K32: =IF(I32<$K$13,J32,$K$13-$J$13) -> 49 | L32: =IF(I32<$L$13,IF(I32-$K$13<0,0,I32-$K$13),IF(I32<$L$13,$L$13-I32,365)) -> 365 | M32: =IF(I32<$M$13,IF(I32-$L$13<0,0,I32-$L$13),IF(I32<$M$13,$M$13-I32,365-($M$13-I32))) -> 866 | O32: =(1+Comparador!$K$30)^(Dados!K32/365) -> 1.0066615 | P32: =(1+Comparador!$L$30)^(Dados!L32/365) -> 1.0443 | Q32: =(1+Comparador!$M$30)^(Dados!M32/365) -> 1.0975223 | S32: =O32*P32*Q32-1 -> 0.15377752 | U32: =(1+S32)^(365/J32)-1 -> 0.04163244
G34: =U34 -> 0.041113541 | I34: =Comparador!F19 -> 47849 | J34: =I34-$J$13 -> 1876 | K34: =IF(I34<$K$13,J34,$K$13-$J$13) -> 49 | L34: =IF(I34<$L$13,IF(I34-$K$13<0,0,I34-$K$13),IF(I34<$L$13,$L$13-I34,365)) -> 365 | M34: =IF(I34<$M$13,IF(I34-$L$13<0,0,I34-$L$13),IF(I34<$M$13,$M$13-I34,365-($M$13-I34))) -> 1462 | O34: =(1+Comparador!$K$30)^(Dados!K34/365) -> 1.0066615 | P34: =(1+Comparador!$L$30)^(Dados!L34/365) -> 1.0443 | Q34: =(1+Comparador!$M$30)^(Dados!M34/365) -> 1.17011 | S34: =O34*P34*Q34-1 -> 0.23008583 | U34: =(1+S34)^(365/J34)-1 -> 0.041113541
G36: =U36 -> 0.04062325 | I36: =Comparador!F21 -> 49324 | J36: =I36-$J$13 -> 3351 | K36: =IF(I36<$K$13,J36,$K$13-$J$13) -> 49 | L36: =IF(I36<$L$13,IF(I36-$K$13<0,0,I36-$K$13),IF(I36<$L$13,$L$13-I36,365)) -> 365 | M36: =IF(I36<$M$13,IF(I36-$L$13<0,0,I36-$L$13),IF(I36<$M$13,$M$13-I36,365-($M$13-I36))) -> 2937 | O36: =(1+Comparador!$K$30)^(Dados!K36/365) -> 1.0066615 | P36: =(1+Comparador!$L$30)^(Dados!L36/365) -> 1.0443 | Q36: =(1+Comparador!$M$30)^(Dados!M36/365) -> 1.3710713 | S36: =O36*P36*Q36-1 -> 0.44134774 | U36: =(1+S36)^(365/J36)-1 -> 0.04062325
G38: =U38 -> 0.0507 | I38: =Comparador!F23 -> 0 | J38: =I38-$J$13 -> -45973 | K38: =IF(I38<$K$13,J38,$K$13-$J$13) -> -45973 | L38: =IF(I38<$L$13,IF(I38-$K$13<0,0,I38-$K$13),IF(I38<$L$13,$L$13-I38,365)) -> 0 | M38: =IF(I38<$M$13,IF(I38-$L$13<0,0,I38-$L$13),IF(I38<$M$13,$M$13-I38,365-($M$13-I38))) -> 0 | O38: =(1+Comparador!$K$30)^(Dados!K38/365) -> 0.0019709705 | P38: =(1+Comparador!$L$30)^(Dados!L38/365) -> 1 | Q38: =(1+Comparador!$M$30)^(Dados!M38/365) -> 1 | S38: =O38*P38*Q38-1 -> -0.99802903 | U38: =(1+S38)^(365/J38)-1 -> 0.0507

Sheet Disclaimer
